xrootd_utils/__init__.py
xrootd_utils/client.py
xrootd_utils/common.py
xrootd_utils/handlers/backup_handler.py
xrootd_utils/handlers/progress_handler.py
xrootd_utils/handlers/restore_handler.py
xrootd_utils/main.py
xrootd_utils-0.1.0.dist-info/METADATA
xrootd_utils-0.1.0.dist-info/WHEEL
xrootd_utils-0.1.0.dist-info/entry_points.txt
xrootd_utils-0.1.0.dist-info/licenses/LICENSE
xrootd_utils-0.1.0.dist-info/RECORD
