Metadata-Version: 2.4
Name: xrootd-utils
Version: 0.1.0
Summary: A collection of high-level utility scripts for moving data to and from offline archival storage using XRootD.
License: MIT
License-File: LICENSE
Author: Patrick Austin
Author-email: patrick.austin@stfc.ac.uk
Requires-Python: >=3.11, <3.14
Classifier: License :: OSI Approved :: MIT License
Classifier: Programming Language :: Python :: 3
Classifier: Programming Language :: Python :: 3.11
Classifier: Programming Language :: Python :: 3.12
Classifier: Programming Language :: Python :: 3.13
Requires-Dist: xrootd (==5.8.2)
